at/_version.py
at/constants.py
at/__init__.py
at/cconfig.cpython-313-darwin.so
at/cconfig.pyi
at/future.py
at/matching/globalfit.py
at/matching/__init__.py
at/matching/matching.py
at/plot/specific.py
at/plot/standalone.py
at/plot/response_matrix.py
at/plot/generic.py
at/plot/resonances.py
at/plot/__init__.py
at/plot/synopt.py
at/collective/haissinski.py
at/collective/__init__.py
at/collective/wake_object.py
at/collective/wake_elements.py
at/collective/wake_functions.py
at/collective/beam_loading.py
at/integrators/StrMPoleSymplectic4QuantPass.cpython-313-darwin.so
at/integrators/QuantDiffPass.cpython-313-darwin.so
at/integrators/ChangePRefPass.cpython-313-darwin.so
at/integrators/VariableThinMPolePass.cpython-313-darwin.so
at/integrators/BndStrMPoleSymplectic4Pass.cpython-313-darwin.so
at/integrators/MatrixTijkPass.cpython-313-darwin.so
at/integrators/ExactMultipoleRadPass.cpython-313-darwin.so
at/integrators/ExactMultipolePass.cpython-313-darwin.so
at/integrators/GWigSymplecticPass.cpython-313-darwin.so
at/integrators/WiggLinearPass.cpython-313-darwin.so
at/integrators/ExactRectBendPass.cpython-313-darwin.so
at/integrators/ExactSectorBendRadPass.cpython-313-darwin.so
at/integrators/CorrectorPass.cpython-313-darwin.so
at/integrators/pyDriftPass.py
at/integrators/TestRandomPass.cpython-313-darwin.so
at/integrators/BendLinearPass.cpython-313-darwin.so
at/integrators/AperturePass.cpython-313-darwin.so
at/integrators/__init__.py
at/integrators/ExactRectangularBendRadPass.cpython-313-darwin.so
at/integrators/BndOldRadPass.cpython-313-darwin.so
at/integrators/QuadLinearFPass.cpython-313-darwin.so
at/integrators/BndMPoleSymplectic4E2Pass.cpython-313-darwin.so
at/integrators/ExactHamiltonianPass.cpython-313-darwin.so
at/integrators/ExactSectorBendPass.cpython-313-darwin.so
at/integrators/EAperturePass.cpython-313-darwin.so
at/integrators/BndMPoleSymplectic4Pass.cpython-313-darwin.so
accelerator_toolbox-0.7.1.dist-info/RECORD
accelerator_toolbox-0.7.1.dist-info/WHEEL
accelerator_toolbox-0.7.1.dist-info/top_level.txt
accelerator_toolbox-0.7.1.dist-info/METADATA
accelerator_toolbox-0.7.1.dist-info/licenses/LICENSE
