Metadata-Version: 2.1
Name: accelerator-toolbox
Version: 0.7.1
Summary: Accelerator Toolbox
Author-email: The AT collaboration <atcollab-general@lists.sourceforge.net>
Project-URL: Home, https://github.com/atcollab/at
Project-URL: Github, https://github.com/atcollab/at.git
Project-URL: Issues, https://github.com/atcollab/at/issues
Project-URL: ChangeLog, https://github.com/atcollab/at/releases
Classifier: Development Status :: 4 - Beta
Classifier: Topic :: Scientific/Engineering :: Physics
Classifier: Programming Language :: Python :: 3 :: Only
Classifier: Programming Language :: Python :: 3.7
Classifier: Programming Language :: Python :: 3.8
Classifier: Programming Language :: Python :: 3.9
Classifier: Programming Language :: Python :: 3.10
Classifier: Programming Language :: Python :: 3.11
Classifier: Programming Language :: Python :: 3.12
Classifier: Programming Language :: Python :: 3.13
Classifier: Intended Audience :: Science/Research
Classifier: License :: OSI Approved :: Apache Software License
Classifier: Operating System :: MacOS
Classifier: Operating System :: Microsoft :: Windows
Classifier: Operating System :: POSIX
Requires-Python: >=3.7
License-File: LICENSE
Requires-Dist: scipy >=1.4.0
Requires-Dist: importlib-resources ; python_version < "3.9"
Requires-Dist: numpy <2.0,>=1.16.6 ; python_version <= "3.8"
Requires-Dist: numpy >=1.23.5 ; python_version >= "3.9"
Provides-Extra: dev
Requires-Dist: pytest >=2.9 ; extra == 'dev'
Requires-Dist: pytest-cov ; extra == 'dev'
Requires-Dist: flake8 ; extra == 'dev'
Provides-Extra: doc
Requires-Dist: Sphinx ~=8.1 ; extra == 'doc'
Requires-Dist: myst-parser ; extra == 'doc'
Requires-Dist: myst-nb ; extra == 'doc'
Requires-Dist: pydata-sphinx-theme ; extra == 'doc'
Requires-Dist: sphinx-design ; extra == 'doc'
Requires-Dist: sphinx-copybutton ; extra == 'doc'
Provides-Extra: mpi
Requires-Dist: mpi4py ; extra == 'mpi'
Provides-Extra: plot
Requires-Dist: matplotlib ; extra == 'plot'
